game_of_life/__init__.py
game_of_life/__main__.py
game_of_life/game_logic/__init__.py
game_of_life/game_logic/board_logic.py
game_of_life/gui/__init__.py
game_of_life/gui/gui.py
menkeyshow.conway-0.0.1.dist-info/METADATA
menkeyshow.conway-0.0.1.dist-info/WHEEL
menkeyshow.conway-0.0.1.dist-info/entry_points.txt
menkeyshow.conway-0.0.1.dist-info/top_level.txt
menkeyshow.conway-0.0.1.dist-info/RECORD
