Metadata-Version: 2.1
Name: menkeyshow.conway
Version: 0.0.1
Summary: Python implementation of Conway's Game of Life
Home-page: https://github.com/Menkeyshow/game_of_life
Author: Maximilian Birkenhagen
Author-email: maximilian.birkenhagen@gmail.com
License: UNKNOWN
Platform: UNKNOWN
Classifier: Programming Language :: Python :: 3
Classifier: Operating System :: OS Independent
